grammatical_phrase_splitter/__init__.py
grammatical_phrase_splitter/grammatical_phrase_splitter.py
grammatical_phrase_splitter-0.2.6.dist-info/licenses/LICENSE
grammatical_phrase_splitter-0.2.6.dist-info/METADATA
grammatical_phrase_splitter-0.2.6.dist-info/WHEEL
grammatical_phrase_splitter-0.2.6.dist-info/entry_points.txt
grammatical_phrase_splitter-0.2.6.dist-info/top_level.txt
grammatical_phrase_splitter-0.2.6.dist-info/RECORD
