Metadata-Version: 2.4
Name: grammatical-phrase-splitter
Version: 0.2.6
Summary: A package to split sentences into grammatical segments using OpenAI API
Home-page: https://github.com/ZiweiGu/GP-TSM
Author: Ziwei Gu
Author-email: ziweigu@g.harvard.edu
Classifier: Programming Language :: Python :: 3
Classifier: License :: OSI Approved :: MIT License
Classifier: Operating System :: OS Independent
License-File: LICENSE
Requires-Dist: openai
Requires-Dist: spacy
Dynamic: author
Dynamic: author-email
Dynamic: classifier
Dynamic: description
Dynamic: description-content-type
Dynamic: home-page
Dynamic: license-file
Dynamic: requires-dist
Dynamic: summary
